phonofix/__init__.py
phonofix/backend/__init__.py
phonofix/backend/base.py
phonofix/backend/chinese_backend.py
phonofix/backend/english_backend.py
phonofix/backend/japanese_backend.py
phonofix/backend/stats.py
phonofix/core/engine_interface.py
phonofix/core/events.py
phonofix/core/phonetic_interface.py
phonofix/core/pipeline_corrector.py
phonofix/core/term_config.py
phonofix/core/tokenizer_interface.py
phonofix/core/protocols/__init__.py
phonofix/core/protocols/corrector.py
phonofix/core/protocols/fuzzy.py
phonofix/core/protocols/pipeline.py
phonofix/languages/chinese/__init__.py
phonofix/languages/chinese/candidates.py
phonofix/languages/chinese/config.py
phonofix/languages/chinese/corrector.py
phonofix/languages/chinese/engine.py
phonofix/languages/chinese/filters.py
phonofix/languages/chinese/fuzzy_generator.py
phonofix/languages/chinese/indexing.py
phonofix/languages/chinese/number_variants.py
phonofix/languages/chinese/phonetic_impl.py
phonofix/languages/chinese/replacements.py
phonofix/languages/chinese/scoring.py
phonofix/languages/chinese/tokenizer.py
phonofix/languages/chinese/types.py
phonofix/languages/chinese/utils.py
phonofix/languages/english/__init__.py
phonofix/languages/english/candidates.py
phonofix/languages/english/config.py
phonofix/languages/english/corrector.py
phonofix/languages/english/engine.py
phonofix/languages/english/filters.py
phonofix/languages/english/fuzzy_generator.py
phonofix/languages/english/indexing.py
phonofix/languages/english/phonetic_impl.py
phonofix/languages/english/replacements.py
phonofix/languages/english/scoring.py
phonofix/languages/english/tokenizer.py
phonofix/languages/english/types.py
phonofix/languages/japanese/__init__.py
phonofix/languages/japanese/candidates.py
phonofix/languages/japanese/config.py
phonofix/languages/japanese/corrector.py
phonofix/languages/japanese/engine.py
phonofix/languages/japanese/filters.py
phonofix/languages/japanese/fuzzy_generator.py
phonofix/languages/japanese/indexing.py
phonofix-0.3.1.dist-info/METADATA
phonofix-0.3.1.dist-info/WHEEL
phonofix-0.3.1.dist-info/RECORD
