Metadata-Version: 2.4
Name: phonofix
Version: 0.3.1
Summary: Multilingual phonetic-similarity replacement engine — a proper-noun substitution tool based on phonetic similarity, supporting ASR/LLM post-processing.
Project-URL: Homepage, https://github.com/JonesHong/phonofix
Project-URL: Repository, https://github.com/JonesHong/phonofix
Project-URL: Documentation, https://github.com/JonesHong/phonofix#readme
Author-email: JonesHong <latte831104@gmail.com>
License: MIT
Keywords: asr,chinese,english,llm,nlp,phonetic,phonofix,speech-recognition,text-correction
Classifier: Development Status :: 4 - Beta
Classifier: Intended Audience :: Developers
Classifier: License :: OSI Approved :: MIT License
Classifier: Programming Language :: Python :: 3
Classifier: Programming Language :: Python :: 3.10
Classifier: Programming Language :: Python :: 3.11
Classifier: Programming Language :: Python :: 3.12
Classifier: Topic :: Scientific/Engineering :: Artificial Intelligence
Classifier: Topic :: Text Processing :: Linguistic
Requires-Python: >=3.10
Requires-Dist: cutlet>=0.3.0
Requires-Dist: fugashi>=1.3.0
Requires-Dist: hanziconv>=0.3.2
Requires-Dist: phonemizer>=3.3.0
Requires-Dist: pinyin2hanzi>=0.1.1
Requires-Dist: pypinyin>=0.44.0
Requires-Dist: python-levenshtein>=0.12.2
Requires-Dist: unidic-lite>=1.0.0
Provides-Extra: all
Requires-Dist: cutlet>=0.3.0; extra == 'all'
Requires-Dist: fugashi>=1.3.0; extra == 'all'
Requires-Dist: hanziconv>=0.3.2; extra == 'all'
Requires-Dist: phonemizer>=3.3.0; extra == 'all'
Requires-Dist: pinyin2hanzi>=0.1.1; extra == 'all'
Requires-Dist: pypinyin>=0.44.0; extra == 'all'
Requires-Dist: unidic-lite>=1.0.0; extra == 'all'
Provides-Extra: ch
Requires-Dist: hanziconv>=0.3.2; extra == 'ch'
Requires-Dist: pinyin2hanzi>=0.1.1; extra == 'ch'
Requires-Dist: pypinyin>=0.44.0; extra == 'ch'
Provides-Extra: dev
Requires-Dist: mypy>=1.0.0; extra == 'dev'
Requires-Dist: pytest-cov>=4.0.0; extra == 'dev'
Requires-Dist: pytest>=7.0.0; extra == 'dev'
Requires-Dist: ruff>=0.1.0; extra == 'dev'
Provides-Extra: en
Requires-Dist: phonemizer>=3.3.0; extra == 'en'
Provides-Extra: ja
Requires-Dist: cutlet>=0.3.0; extra == 'ja'
Requires-Dist: fugashi>=1.3.0; extra == 'ja'
Requires-Dist: unidic-lite>=1.0.0; extra == 'ja'
